qsml/__init__.py
qsml/builder.py
qsml/dumperror.py
qsml/error.py
qsml/handler.py
qsml/lexer.py
qsml/parser.py
qsml/token.py
qsml-1.0.1.dist-info/LICENSE
qsml-1.0.1.dist-info/METADATA
qsml-1.0.1.dist-info/WHEEL
qsml-1.0.1.dist-info/top_level.txt
qsml-1.0.1.dist-info/RECORD
