Metadata-Version: 2.1
Name: qsml
Version: 1.0.1
Summary: qsml is a markup language.
Home-page: https://github.com/michaelpeterswa/qsml
Author: Michael Peters
Author-email: michaelpeterswa@icloud.com
License: MIT
Platform: UNKNOWN
Classifier: Programming Language :: Python :: 3
Classifier: License :: OSI Approved :: MIT License
Classifier: Operating System :: OS Independent
Requires-Python: >=3.5
